devops_toolkit/__init__.py
devops_toolkit/cli.py
devops_toolkit/config.py
devops_toolkit/interactive_cli.py
devops_toolkit/logging.py
devops_toolkit/plugins.py
devops_toolkit/secrets.py
devops_toolkit/state.py
devops_toolkit/template_library.py
devops_toolkit/visualization.py
devops_toolkit/tools/__init__.py
devops_toolkit/tools/deployment.py
devops_toolkit/tools/generate-terraform.py
devops_toolkit/tools/infrastructure.py
devops_toolkit/tools/monitoring.py
devops_toolkit/tools/security.py
devops_toolkit-0.1.1.dist-info/METADATA
devops_toolkit-0.1.1.dist-info/WHEEL
devops_toolkit-0.1.1.dist-info/entry_points.txt
devops_toolkit-0.1.1.dist-info/top_level.txt
devops_toolkit-0.1.1.dist-info/RECORD
