Metadata-Version: 2.2
Name: devops-toolkit
Version: 0.1.1
Summary: A comprehensive Python-based toolkit for DevOps workflows
Home-page: https://github.com/kenbark42/devops-toolkit
Author: Kenbark42
Author-email: Kenbark42 <kenbark42@example.com>
License: MIT
Project-URL: Homepage, https://github.com/kenbark42/devops-toolkit
Project-URL: Issues, https://github.com/kenbark42/devops-toolkit/issues
Project-URL: Documentation, https://github.com/kenbark42/devops-toolkit/docs
Classifier: Development Status :: 3 - Alpha
Classifier: Intended Audience :: Developers
Classifier: Intended Audience :: System Administrators
Classifier: License :: OSI Approved :: MIT License
Classifier: Programming Language :: Python :: 3
Classifier: Programming Language :: Python :: 3.8
Classifier: Programming Language :: Python :: 3.9
Classifier: Programming Language :: Python :: 3.10
Classifier: Programming Language :: Python :: 3.11
Classifier: Topic :: Software Development :: Build Tools
Classifier: Topic :: System :: Installation/Setup
Classifier: Topic :: System :: Systems Administration
Requires-Python: >=3.8
Requires-Dist: click>=8.0.0
Requires-Dist: pyyaml>=6.0
Requires-Dist: pydantic>=2.0.0
Requires-Dist: rich>=12.0.0
Provides-Extra: aws
Requires-Dist: boto3>=1.26.0; extra == "aws"
Requires-Dist: botocore>=1.29.0; extra == "aws"
Provides-Extra: kubernetes
Requires-Dist: kubernetes>=24.2.0; extra == "kubernetes"
Provides-Extra: monitoring
Requires-Dist: prometheus-client>=0.16.0; extra == "monitoring"
Requires-Dist: requests>=2.28.0; extra == "monitoring"
Provides-Extra: dev
Requires-Dist: pytest>=7.0.0; extra == "dev"
Requires-Dist: pytest-cov>=4.0.0; extra == "dev"
Requires-Dist: black>=23.0.0; extra == "dev"
Requires-Dist: flake8>=6.0.0; extra == "dev"
Requires-Dist: mypy>=1.0.0; extra == "dev"
Requires-Dist: isort>=5.10.0; extra == "dev"
Requires-Dist: build>=0.10.0; extra == "dev"
Requires-Dist: twine>=4.0.0; extra == "dev"
Provides-Extra: all
Requires-Dist: boto3>=1.26.0; extra == "all"
Requires-Dist: botocore>=1.29.0; extra == "all"
Requires-Dist: kubernetes>=24.2.0; extra == "all"
Requires-Dist: prometheus-client>=0.16.0; extra == "all"
Requires-Dist: requests>=2.28.0; extra == "all"
Dynamic: author
Dynamic: home-page
Dynamic: requires-python
